apigo/__init__.py
apigo/__main__.py
apigo/example.py
apigo/py.typed
apigo-0.1.0.dist-info/entry_points.txt
apigo-0.1.0.dist-info/LICENSE
apigo-0.1.0.dist-info/WHEEL
apigo-0.1.0.dist-info/METADATA
apigo-0.1.0.dist-info/RECORD
