Metadata-Version: 2.1
Name: apigo
Version: 0.1.0
Summary: get a fast REST mock server out of the box
Home-page: https://github.com/nidhaloff/apigo
License: MIT
Author: nidhaloff
Author-email: nidhaloff@gmail.com
Requires-Python: >=3.7,<4.0
Classifier: Development Status :: 3 - Alpha
Classifier: Intended Audience :: Developers
Classifier: License :: OSI Approved :: MIT License
Classifier: Operating System :: OS Independent
Classifier: Programming Language :: Python :: 3
Classifier: Programming Language :: Python :: 3.7
Classifier: Programming Language :: Python :: 3.8
Classifier: Programming Language :: Python :: 3.9
Classifier: Topic :: Software Development :: Libraries :: Python Modules
Requires-Dist: importlib-metadata (>=1.6.0,<2.0.0); python_version >= "3.8" and python_version < "4.0"
Requires-Dist: typer[all] (>=0.3.2,<0.4.0)
Project-URL: Repository, https://github.com/nidhaloff/apigo
